campyStructs/__init__.py
campyStructs/graph.py
campyStructs/linkedList.py
campyStructs-1.0.0.dist-info/DESCRIPTION.rst
campyStructs-1.0.0.dist-info/METADATA
campyStructs-1.0.0.dist-info/RECORD
campyStructs-1.0.0.dist-info/WHEEL
campyStructs-1.0.0.dist-info/metadata.json
campyStructs-1.0.0.dist-info/top_level.txt
