Metadata-Version: 2.0
Name: campyStructs
Version: 1.0.0
Summary: A collection of simple data structures in python
Home-page: https://github.com/Cammac7/campyStructs
Author: Cameron MacArthur
Author-email: cam.mac@gmx.com
License: MIT
Download-URL: https://github.com/Cammac7/campyStructs/archive/0.1.tar.gz
Keywords: data_structures,interviews,practice
Platform: UNKNOWN
Classifier: Development Status :: 3 - Alpha
Classifier: Intended Audience :: Developers
Classifier: Topic :: Software Development :: Build Tools
Classifier: License :: OSI Approved :: MIT License
Classifier: Programming Language :: Python :: 3
Classifier: Programming Language :: Python :: 3.2
Classifier: Programming Language :: Python :: 3.3
Classifier: Programming Language :: Python :: 3.4
Classifier: Programming Language :: Python :: 3.5
Classifier: Programming Language :: Python :: 3.6
Requires-Python: >=3
